nuromind/__init__.py
nuromind/config.py
nuromind/core.py
nuromind/utils.py
nuromind/imaging/__init__.py
nuromind/imaging/preprocessing.py
nuromind/llm/__init__.py
nuromind/llm/assistant.py
nuromind/microbiome/__init__.py
nuromind/microbiome/analysis.py
nuromind/models/__init__.py
nuromind/models/alzheimer.py
nuromind/models/base.py
nuromind-0.0.2.dist-info/LICENSE
nuromind-0.0.2.dist-info/METADATA
nuromind-0.0.2.dist-info/WHEEL
nuromind-0.0.2.dist-info/top_level.txt
nuromind-0.0.2.dist-info/RECORD
