Metadata-Version: 2.1
Name: nuromind
Version: 0.0.2
Summary: A neuroscience ML library for Alzheimer's disease research with microbiome integration and LLM capabilities
Home-page: https://github.com/melhzy/nuromind
Author: Ziyuan Huang
Author-email: Ziyuan Huang <ziyuan.huang2@umassmed.edu>
License: MIT
Project-URL: Homepage, https://github.com/melhzy/nuromind
Project-URL: Issues, https://github.com/melhzy/nuromind/issues
Project-URL: Repository, https://github.com/melhzy/nuromind
Keywords: neuroscience,alzheimer,microbiome,machine-learning,deep-learning
Classifier: Development Status :: 2 - Pre-Alpha
Classifier: Intended Audience :: Science/Research
Classifier: Topic :: Scientific/Engineering :: Bio-Informatics
Classifier: Topic :: Scientific/Engineering :: Medical Science Apps.
Classifier: Topic :: Scientific/Engineering :: Artificial Intelligence
Classifier: License :: OSI Approved :: MIT License
Classifier: Programming Language :: Python :: 3
Classifier: Programming Language :: Python :: 3.8
Classifier: Programming Language :: Python :: 3.9
Classifier: Programming Language :: Python :: 3.10
Classifier: Programming Language :: Python :: 3.11
Classifier: Programming Language :: Python :: 3.12
Requires-Python: >=3.8
License-File: LICENSE
Requires-Dist: torch >=2.0.0
Requires-Dist: transformers >=4.30.0
Requires-Dist: datasets >=2.14.0
Requires-Dist: huggingface-hub >=0.16.0
Requires-Dist: openai >=1.0.0
Requires-Dist: langchain >=0.1.0
Requires-Dist: chromadb >=0.4.0
Requires-Dist: monai >=1.3.0
Requires-Dist: numpy >=1.21.0
Requires-Dist: pandas >=1.3.0
Requires-Dist: scikit-learn >=1.0.0
Requires-Dist: matplotlib >=3.5.0
Requires-Dist: seaborn >=0.12.0
Requires-Dist: tqdm >=4.65.0
Provides-Extra: bio
Requires-Dist: biopython >=1.79 ; extra == 'bio'
Requires-Dist: scikit-bio >=0.5.7 ; extra == 'bio'
Provides-Extra: dev
Requires-Dist: pytest >=7.0.0 ; extra == 'dev'
Requires-Dist: pytest-cov >=4.0.0 ; extra == 'dev'
Requires-Dist: black >=22.0.0 ; extra == 'dev'
Requires-Dist: flake8 >=5.0.0 ; extra == 'dev'
Requires-Dist: mypy >=1.0.0 ; extra == 'dev'
Requires-Dist: build >=0.10.0 ; extra == 'dev'
Requires-Dist: twine >=4.0.0 ; extra == 'dev'
Provides-Extra: microbiome
Requires-Dist: biom-format >=2.1.12 ; extra == 'microbiome'
Requires-Dist: unifrac >=1.1 ; extra == 'microbiome'
Provides-Extra: viz
Requires-Dist: plotly >=5.0.0 ; extra == 'viz'
Requires-Dist: bokeh >=3.0.0 ; extra == 'viz'
